{"about":"The Carl H. Lindner College of Business Student Action Team aims to represent every undergraduate business major at the University of Cincinnati. ","awards":"2013 Lindner Student Organization of the Year","category":"Organization","category_list":[{"id":"198503866828628","name":"Organization"}],"checkins":5,"founded":"Fall 2011","general_info":"Find us online:\n\nTwitter: @lcbsat\nWebsite: www.lindnerstudent.com","is_published":true,"location":{"street":"2925 Campus Green Drive","city":"Cincinnati","state":"OH","country":"United States","zip":"45221","latitude":39.13435,"longitude":-84.514295},"mission":"The Lindner College of Business Student Action Team will form a united undergraduate student body with the Carl H. Lindner College of Business that encourages an engaging atmosphere to foster student innovation, and allows students to pursue opportunities through tangible actions to establish a legacy of bettering the University of Cincinnati. ","talking_about_count":5,"username":"studentactionteam","website":"http:\/\/www.lindnerstudent.com","were_here_count":5,"id":"271720546262181","name":"Carl H. Lindner College of Business Student Action Team","link":"http:\/\/www.facebook.com\/studentactionteam","likes":220,"cover":{"cover_id":475310159236551,"source":"http:\/\/sphotos-d.ak.fbcdn.net\/hphotos-ak-frc3\/t1.0-9\/s720x720\/1981757_475310159236551_1613474616_n.jpg","offset_y":14,"offset_x":0}}